ycbvideo/VERSION
ycbvideo/__init__.py
ycbvideo/__main__.py
ycbvideo/descriptor_creation.py
ycbvideo/frame_access.py
ycbvideo/frame_info.txt
ycbvideo/info.py
ycbvideo/loader.py
ycbvideo/parsing.py
ycbvideo/selectors.py
ycbvideo/utils.py
ycbvideo-0.7.0.dist-info/LICENSE
ycbvideo-0.7.0.dist-info/METADATA
ycbvideo-0.7.0.dist-info/WHEEL
ycbvideo-0.7.0.dist-info/top_level.txt
ycbvideo-0.7.0.dist-info/RECORD
